callabletype.py
callabletype-1.0.1.dist-info/licenses/LICENSE
callabletype-1.0.1.dist-info/METADATA
callabletype-1.0.1.dist-info/WHEEL
callabletype-1.0.1.dist-info/top_level.txt
callabletype-1.0.1.dist-info/RECORD
